{
  "timestamp": "2025-12-13T23:05:39.117059",
  "task_statistics": [
    {
      "app_name": "fast_task",
      "app_weight": 1,
      "total_workunits": 5,
      "pending_results": 0,
      "in_progress_results": 0,
      "completed_results": 5,
      "failed_results": 0,
      "avg_elapsed_time": 4.884372600000001,
      "avg_cpu_time": 0,
      "avg_credit": 0.011306418055555555,
      "total_credit": 0.05653209027777777,
      "avg_queue_time": 9.6,
      "avg_execution_time": 27.8,
      "min_elapsed_time": 1.007272,
      "max_elapsed_time": 12.835215
    },
    {
      "app_name": "long_task",
      "app_weight": 1,
      "total_workunits": 5,
      "pending_results": 0,
      "in_progress_results": 0,
      "completed_results": 5,
      "failed_results": 0,
      "avg_elapsed_time": 9.4575568,
      "avg_cpu_time": 0,
      "avg_credit": 0.021892492592592593,
      "total_credit": 0.10946246296296297,
      "avg_queue_time": 8.2,
      "avg_execution_time": 27.8,
      "min_elapsed_time": 6.031553,
      "max_elapsed_time": 14.844913
    },
    {
      "app_name": "medium_task",
      "app_weight": 1,
      "total_workunits": 5,
      "pending_results": 0,
      "in_progress_results": 0,
      "completed_results": 5,
      "failed_results": 0,
      "avg_elapsed_time": 8.4550102,
      "avg_cpu_time": 0,
      "avg_credit": 0.01957178287037037,
      "total_credit": 0.09785891435185184,
      "avg_queue_time": 8.0,
      "avg_execution_time": 27.6,
      "min_elapsed_time": 3.014699,
      "max_elapsed_time": 15.849863
    },
    {
      "app_name": "random_task",
      "app_weight": 1,
      "total_workunits": 5,
      "pending_results": 0,
      "in_progress_results": 0,
      "completed_results": 5,
      "failed_results": 0,
      "avg_elapsed_time": 8.099209400000001,
      "avg_cpu_time": 0,
      "avg_credit": 0.018748169907407408,
      "total_credit": 0.09374084953703704,
      "avg_queue_time": 8.2,
      "avg_execution_time": 30.2,
      "min_elapsed_time": 3.00713,
      "max_elapsed_time": 13.839524
    }
  ],
  "client_statistics": [
    {
      "host_id": 10,
      "host_name": "boinc-client-4",
      "host_fpops": 1000000000,
      "total_results": 5,
      "completed_results": 5,
      "failed_results": 0,
      "in_progress_results": 0,
      "fast_task_completed": 2,
      "medium_task_completed": 1,
      "long_task_completed": 1,
      "random_task_completed": 1,
      "avg_elapsed_time": 3.2164238,
      "total_credit": 0.03722712731481481,
      "last_completion_time": 1765656239,
      "last_rpc_time": 1765656239,
      "host_create_time": 1765656190,
      "first_task_sent_time": 1765656213,
      "idle_time_seconds": 100,
      "has_active_tasks": false,
      "time_since_last_rpc_seconds": 100,
      "time_since_connect_seconds": 149
    },
    {
      "host_id": 11,
      "host_name": "boinc-client-15",
      "host_fpops": 1000000000,
      "total_results": 13,
      "completed_results": 13,
      "failed_results": 0,
      "in_progress_results": 0,
      "fast_task_completed": 3,
      "medium_task_completed": 4,
      "long_task_completed": 3,
      "random_task_completed": 3,
      "avg_elapsed_time": 9.815990384615384,
      "total_credit": 0.295388599537037,
      "last_completion_time": 1765656241,
      "last_rpc_time": 1765656241,
      "host_create_time": 1765656193,
      "first_task_sent_time": 1765656204,
      "idle_time_seconds": 98,
      "has_active_tasks": false,
      "time_since_last_rpc_seconds": 98,
      "time_since_connect_seconds": 146
    },
    {
      "host_id": 12,
      "host_name": "boinc-client-13",
      "host_fpops": 1000000000,
      "total_results": 2,
      "completed_results": 2,
      "failed_results": 0,
      "in_progress_results": 0,
      "fast_task_completed": 0,
      "medium_task_completed": 0,
      "long_task_completed": 1,
      "random_task_completed": 1,
      "avg_elapsed_time": 5.3953755,
      "total_credit": 0.024978590277777775,
      "last_completion_time": 1765656230,
      "last_rpc_time": 1765656230,
      "host_create_time": 1765656193,
      "first_task_sent_time": 1765656204,
      "idle_time_seconds": 109,
      "has_active_tasks": false,
      "time_since_last_rpc_seconds": 109,
      "time_since_connect_seconds": 146
    }
  ]
}